atmos_cloud_sim_uj_utils/__init__.py
atmos_cloud_sim_uj_utils/pip_install_on_colab.py
atmos_cloud_sim_uj_utils/show_plot.py
atmos_cloud_sim_uj_utils/temporary_file.py
atmos_cloud_sim_uj_utils-0.7.dist-info/LICENSE
atmos_cloud_sim_uj_utils-0.7.dist-info/METADATA
atmos_cloud_sim_uj_utils-0.7.dist-info/WHEEL
atmos_cloud_sim_uj_utils-0.7.dist-info/top_level.txt
atmos_cloud_sim_uj_utils-0.7.dist-info/RECORD
