Metadata-Version: 2.1
Name: atmos-cloud-sim-uj-utils
Version: 0.7
Summary: utility routines used in PySDM and PyMPDATA examples and tests
Author: https://github.com/atmos-cloud-sim-uj/utils/graphs/contributors
Author-email: sylwester.arabas@uj.edu.pl
License: GPL-3.0
Project-URL: Tracker, https://github.com/atmos-cloud-sim-uj/utils/issues
Project-URL: Documentation, https://atmos-cloud-sim-uj.github.io/utils
Project-URL: Source, https://github.com/atmos-cloud-sim-uj/utils
License-File: LICENSE
Requires-Dist: ipywidgets
Requires-Dist: IPython
Requires-Dist: matplotlib
